{"course_code": "MATH345", "total_reviews": 1, "instructors": [{"professor_id": "69427", "professor_name": "Ladislav Stacho", "avg_rating": 5.0, "avg_difficulty": 3.0, "review_count": 1, "reviews": [{"rating": 5.0, "difficulty": 3.0, "course_code": "MATH345", "date": "Dec 15th, 2019", "metadata": {"For Credit": "Yes", "Attendance": "Not Mandatory", "Would Take Again": "Yes", "Grade": "", "Textbook": "Yes"}, "review_msg": "He is one of the best profs I have ever had. His clarity and knowledge of graph theory was obviously immaculate but the way he brought up profs and explained interesting problems was incredible. This will probably get banned but sometimes I would legit feel aroused after class because of how exciting the lectures were.", "helpful": 0, "not_helpful": 0, "tags": ["Gives good feedback", "Respected", "Inspirational"]}]}]}