{"professor_id": "1714566", "professor_name": "Ellexis Boyle", "overall_rating": "5", "would_take_again": "N/A", "difficulty_level": "2.5", "department": "Gender Studies department", "total_ratings": "2", "reviews": [{"rating": "5.0", "difficulty": "2.0", "course_code": "GSWS330", "date": "Apr 27th, 2012", "metadata": {"Textbook": "Yes"}, "review_msg": "I am fairly certain this was one of the first classes Professor Boyle has taught, and I think she did a fantastic job! She is a tough marker, but presents very clear expectations. Her lectures were varied with guest speakers, presentations, documentaries and discussions. A fantastic class all around! GSWS department, you better keep her!", "helpful": "0", "not_helpful": "0", "tags": []}, {"rating": "5.0", "difficulty": "3.0", "course_code": "GSWS330", "date": "Apr 25th, 2012", "metadata": {"Textbook": "Yes"}, "review_msg": "Ellexis brings an incredibly varied background to the table: Human kinetics, chef training, and gender studies. Made for a crazy interesting Masculinity Studies class. She's a tough marker, but gives you a rubric beforehand. Really enjoyed her perspective on things, and she was always super kind and approachable.", "helpful": "0", "not_helpful": "0", "tags": []}]}