{"professor_id": "31009", "professor_name": "Martin Kitchen", "overall_rating": "2.8", "would_take_again": "N/A", "difficulty_level": "3.4", "department": "History department", "total_ratings": "15", "reviews": [{"rating": "3.5", "difficulty": "2.0", "course_code": "HISTORY", "date": "Dec 28th, 2014", "metadata": {"For Credit": "Yes", "Textbook": "Yes"}, "review_msg": "Dr. Kitchen was an absolutely amazing prof. I took many of his classes and always looked forward to his lectures and tutorials. Great stuff.", "helpful": "0", "not_helpful": "0", "tags": []}, {"rating": "4.5", "difficulty": "3.0", "course_code": "HISTORY", "date": "Oct 28th, 2014", "metadata": {"For Credit": "Yes", "Textbook": "Yes"}, "review_msg": "I took several courses from Dr.. Kitchen while doing my history degree. It was a pleasure to learn from such an accomplished and passionate historian.  He always was most helpful when I had questions and was generous with his time.", "helpful": "0", "not_helpful": "0", "tags": []}, {"rating": "5.0", "difficulty": "4.0", "course_code": "HIST201", "date": "Jan 15th, 2010", "metadata": {"Textbook": "Yes"}, "review_msg": "Amazing, interesting, engaging, passionate, talented.", "helpful": "0", "not_helpful": "0", "tags": []}, {"rating": "1.0", "difficulty": "4.0", "course_code": "HIST225", "date": "Oct 19th, 2008", "metadata": {"Textbook": "Yes"}, "review_msg": "Horrible professor.  Would cancel class to do research for his next book.  Would only use his text in class - money grab.  Knew material but didn't know how to teach.", "helpful": "0", "not_helpful": "0", "tags": []}, {"rating": "3.5", "difficulty": "3.0", "course_code": "HIST", "date": "Feb 9th, 2006", "metadata": {}, "review_msg": "Excellent prof. I took several European history and WW2 courses from him. Dr. Kitchen captivated me with his vast experience and insightful stories. He made it exciting to come to class. I am dissapointed that he will not be teaching this semester.", "helpful": "0", "not_helpful": "0", "tags": []}, {"rating": "1.0", "difficulty": "4.0", "course_code": "HIST", "date": "Apr 2nd, 2005", "metadata": {}, "review_msg": "Horrible instructor.", "helpful": "0", "not_helpful": "0", "tags": []}, {"rating": "1.0", "difficulty": "4.0", "course_code": "HIST225", "date": "Dec 3rd, 2004", "metadata": {}, "review_msg": "Kept cancelling classes to travel to Europe.  Very arrogant.  Stay away if you can.", "helpful": "0", "not_helpful": "0", "tags": []}, {"rating": "5.0", "difficulty": "3.0", "course_code": "HIST225", "date": "Aug 6th, 2004", "metadata": {}, "review_msg": "Amazing, best professor I have ever had. He is intelligence and writes amazing works of history.Wish we had more like him.....", "helpful": "0", "not_helpful": "0", "tags": []}, {"rating": "5.0", "difficulty": "4.0", "course_code": "HIST225", "date": "Jul 10th, 2004", "metadata": {}, "review_msg": "He is the best professor I have ever had!", "helpful": "0", "not_helpful": "0", "tags": []}, {"rating": "3.5", "difficulty": "3.0", "course_code": "HIST225", "date": "Apr 4th, 2004", "metadata": {}, "review_msg": "Whoa guys, cool it! I had him a while ago, maybe he's gotten old, but I don't remember him as bad at all. Actually reminded me of Indiana Jones's English sidesick going off on int'l expeditions on the weekends. Seemed knowledgeable enough", "helpful": "0", "not_helpful": "0", "tags": []}, {"rating": "1.0", "difficulty": "3.0", "course_code": "HST205", "date": "Feb 19th, 2004", "metadata": {}, "review_msg": "Arrogant piece of work. He lost part of my midterm (10 % of my entire grade) blamed it on me (accusing me of cheating) then left the country.  I got 0 for 10% of my final grade.  To boot, the history dpmt stood beside this fine specimen of an intellect.", "helpful": "0", "not_helpful": "0", "tags": []}, {"rating": "1.0", "difficulty": "5.0", "course_code": "HIST", "date": "Jul 1st, 2003", "metadata": {}, "review_msg": "Man appears to be senile. Talks about irrelevant things, drifts in and out of material and leaves you hanging. Will often ignore you if he does not like your questions.", "helpful": "0", "not_helpful": "0", "tags": []}, {"rating": "4.0", "difficulty": "4.0", "course_code": "HIST225", "date": "Mar 20th, 2003", "metadata": {}, "review_msg": "No Comments", "helpful": "0", "not_helpful": "0", "tags": []}, {"rating": "2.0", "difficulty": "4.0", "course_code": "HIST225", "date": "Feb 8th, 2003", "metadata": {}, "review_msg": "No Comments", "helpful": "0", "not_helpful": "0", "tags": []}, {"rating": "1.0", "difficulty": "1.0", "course_code": "HIST225", "date": "Dec 4th, 2002", "metadata": {}, "review_msg": "A major disappointment.  Totaly unhelpful and out of touch.", "helpful": "0", "not_helpful": "0", "tags": []}]}