{"course_code": "SCFCSCFC", "total_reviews": 1, "instructors": [{"professor_id": "187960", "professor_name": "Harvey DeRoo", "avg_rating": 3.0, "avg_difficulty": 1.0, "review_count": 1, "reviews": [{"rating": 3.0, "difficulty": 1.0, "course_code": "SCFCSCFC", "date": "Oct 28th, 2012", "metadata": {"For Credit": "", "Attendance": "", "Would Take Again": "", "Grade": "", "Textbook": "No"}, "review_msg": "Poorly photo-copied handouts of a general opera guide, plus disorganized presentation of material does not rate high in my books. Sometimes retirement means just that: Retire, sir.", "helpful": 0, "not_helpful": 0, "tags": []}]}]}