{"course_code": "FPA120", "total_reviews": 1, "instructors": [{"professor_id": "88694", "professor_name": "Janet Danielson", "avg_rating": 1.0, "avg_difficulty": 5.0, "review_count": 1, "reviews": [{"rating": 1.0, "difficulty": 5.0, "course_code": "FPA120", "date": "Nov 27th, 2010", "metadata": {"For Credit": "", "Attendance": "", "Would Take Again": "", "Grade": "", "Textbook": "Yes"}, "review_msg": "Taking this class with Danielson was the worst decision of my entire university career. She is completely useless and relies completely on the textbook that SHE wrote. She has managed to make a potentially enjoyable class into a HUGE pain. AVOID AVOID AVOID!!", "helpful": 0, "not_helpful": 0, "tags": []}]}]}