{"course_code": "FPA246", "total_reviews": 4, "instructors": [{"professor_id": "28589", "professor_name": "David MacIntyre", "avg_rating": 3.25, "avg_difficulty": 4.25, "review_count": 4, "reviews": [{"rating": 5.0, "difficulty": 4.0, "course_code": "FPA246", "date": "Sep 30th, 2016", "metadata": {"For Credit": "Yes", "Attendance": "Mandatory", "Would Take Again": "Yes", "Grade": "", "Textbook": "No"}, "review_msg": "one of the best I've ever had!", "helpful": 2, "not_helpful": 2, "tags": ["Tough Grader", "Gives good feedback", "Respected"]}, {"rating": 5.0, "difficulty": 4.0, "course_code": "FPA246", "date": "Apr 25th, 2016", "metadata": {"For Credit": "Yes", "Attendance": "Mandatory", "Would Take Again": "", "Grade": "", "Textbook": "No"}, "review_msg": "Cool Prof. who knows his stuff. He is kind and generous in tutorials where the action is. Listen, work hard and show up, you'll do well. He likes students to show up!", "helpful": 3, "not_helpful": 1, "tags": []}, {"rating": 2.0, "difficulty": 4.0, "course_code": "FPA246", "date": "Jan 26th, 2014", "metadata": {"For Credit": "", "Attendance": "", "Would Take Again": "", "Grade": "A-", "Textbook": "No"}, "review_msg": "This guy was so awful I almost quit after my first week. He was rude and insulting. He thinks he knows everything, but he doesn't even have a doctorate. To be honest, I'm not sure I'd recommend studying composition at SFU. I definitely didn't get what I paid for.", "helpful": 2, "not_helpful": 5, "tags": []}, {"rating": 1.0, "difficulty": 5.0, "course_code": "FPA246", "date": "Aug 16th, 2007", "metadata": {"For Credit": "", "Attendance": "", "Would Take Again": "", "Grade": "", "Textbook": "No"}, "review_msg": "Nice if he likes you but randomly chooses people he hates and makes their life a living hell.", "helpful": 1, "not_helpful": 3, "tags": []}]}]}