{"course_code": "354450", "total_reviews": 1, "instructors": [{"professor_id": "192102", "professor_name": "Bryan Sokol", "avg_rating": 4.5, "avg_difficulty": 2.0, "review_count": 1, "reviews": [{"rating": 4.5, "difficulty": 2.0, "course_code": "354450", "date": "Aug 10th, 2004", "metadata": {"For Credit": "", "Attendance": "", "Would Take Again": "", "Grade": "", "Textbook": ""}, "review_msg": "Bryan knows his stuff. He shines more in a smaller classroom than a lecture hall; he expects a lot from his students but if you put in the effort you will feel more than amply rewarded.", "helpful": 0, "not_helpful": 0, "tags": []}]}]}