{"course_code": "CMPT200", "total_reviews": 1, "instructors": [{"professor_id": "20266", "professor_name": "Brad Bart", "avg_rating": 4.5, "avg_difficulty": 3.0, "review_count": 1, "reviews": [{"rating": 4.5, "difficulty": 3.0, "course_code": "CMPT200", "date": "Sep 11th, 2003", "metadata": {"For Credit": "", "Attendance": "", "Would Take Again": "", "Grade": "", "Textbook": ""}, "review_msg": "really tough on grading. touch assignments. easy exams. smart and humorous guy with tough attitude when it comes to grading.", "helpful": 0, "not_helpful": 0, "tags": []}]}]}