{"course_code": "CMPT882", "total_reviews": 2, "instructors": [{"professor_id": "262659", "professor_name": "Oliver Schulte", "avg_rating": 1.25, "avg_difficulty": 3.0, "review_count": 2, "reviews": [{"rating": 1.0, "difficulty": 1.0, "course_code": "CMPT882", "date": "May 15th, 2011", "metadata": {"For Credit": "", "Attendance": "", "Would Take Again": "", "Grade": "", "Textbook": "No"}, "review_msg": "He set 30% (or 40%) for assignments. And there were just two sets of assignments. The questions were absolutely nonsense and funny. He himself even didn't know what his questions meant. He was totally unable to teach.", "helpful": 5, "not_helpful": 0, "tags": []}, {"rating": 1.5, "difficulty": 5.0, "course_code": "CMPT882", "date": "May 13th, 2011", "metadata": {"For Credit": "", "Attendance": "", "Would Take Again": "", "Grade": "", "Textbook": "No"}, "review_msg": "The most ridiculous course and professor. In the graduate level, at Game Theory, the whole time he was just practicing games like prisoners dilemma, chicken and Rock-paper-scissors, . . . and gave chocolates to the winners or volunteers!! Such a picnic!!", "helpful": 11, "not_helpful": 0, "tags": []}]}]}