{"course_code": "ECONO103", "total_reviews": 1, "instructors": [{"professor_id": "886423", "professor_name": "Mohammed Akbar", "avg_rating": 1.5, "avg_difficulty": 2.0, "review_count": 1, "reviews": [{"rating": 1.5, "difficulty": 2.0, "course_code": "ECONO103", "date": "Nov 15th, 2006", "metadata": {"For Credit": "", "Attendance": "", "Would Take Again": "", "Grade": "", "Textbook": "Yes"}, "review_msg": "Don't let his thick accent deceive you. Hidden underneath that accent is a big heart. He gives very difficult quizes which are worth 1%-2%. You then go over it in tutorials and when the real midterms come, Its easier or literally the same type of question. He wants all his students to do good. Can't understand anything in his lectures though.", "helpful": 0, "not_helpful": 0, "tags": []}]}]}