{"course_code": "ENG472W", "total_reviews": 1, "instructors": [{"professor_id": "1830216", "professor_name": "Broc Rossell", "avg_rating": 5.0, "avg_difficulty": 1.0, "review_count": 1, "reviews": [{"rating": 5.0, "difficulty": 1.0, "course_code": "ENG472W", "date": "Dec 4th, 2014", "metadata": {"For Credit": "Yes", "Attendance": "", "Would Take Again": "", "Grade": "A", "Textbook": "Yes"}, "review_msg": "Powerful command over the English language, lovely to listen to. Even better that he has a great sense of humour, and genuinely cares for the well-being of his students. You don't come across a professor like this very often. One of the best profs out there for sure.", "helpful": 5, "not_helpful": 9, "tags": []}]}]}