{"course_code": "ENGL492", "total_reviews": 1, "instructors": [{"professor_id": "28899", "professor_name": "Paul St. Pierre", "avg_rating": 5.0, "avg_difficulty": 3.0, "review_count": 1, "reviews": [{"rating": 5.0, "difficulty": 3.0, "course_code": "ENGL492", "date": "Apr 7th, 2014", "metadata": {"For Credit": "", "Attendance": "", "Would Take Again": "", "Grade": "", "Textbook": "Yes"}, "review_msg": "Paul is the best professor you could possibly have if you have a very creative mind. He is open to different mediums of academia and he has an appreciation for them. His dedication to his students is so touching and we all appreciated how understand or compassionate he was towards time management. He is just amazing.", "helpful": 1, "not_helpful": 1, "tags": []}]}]}