{"course_code": "ENGL311204", "total_reviews": 1, "instructors": [{"professor_id": "88852", "professor_name": "Anne Higgins", "avg_rating": 5.0, "avg_difficulty": 1.0, "review_count": 1, "reviews": [{"rating": 5.0, "difficulty": 1.0, "course_code": "ENGL311204", "date": "Jun 27th, 2005", "metadata": {"For Credit": "", "Attendance": "", "Would Take Again": "", "Grade": "", "Textbook": ""}, "review_msg": "Lovely lady, very caring, will help you however she can. Very sweet - quite disorganized - was late for the final. But that's okay with me.", "helpful": 0, "not_helpful": 7, "tags": []}]}]}