{"course_code": "IS320", "total_reviews": 2, "instructors": [{"professor_id": "886423", "professor_name": "Mohammed Akbar", "avg_rating": 1.5, "avg_difficulty": 3.5, "review_count": 2, "reviews": [{"rating": 2.0, "difficulty": 3.0, "course_code": "IS320", "date": "Feb 11th, 2008", "metadata": {"For Credit": "", "Attendance": "", "Would Take Again": "", "Grade": "", "Textbook": "Yes"}, "review_msg": "He is very rude with his students and never wants to help any student.", "helpful": 0, "not_helpful": 0, "tags": []}, {"rating": 1.0, "difficulty": 4.0, "course_code": "IS320", "date": "Jan 27th, 2008", "metadata": {"For Credit": "", "Attendance": "", "Would Take Again": "", "Grade": "", "Textbook": "No"}, "review_msg": "You wouldn't understand  his lectures because of his accent. He is so mean as well. Never get a course with him.", "helpful": 0, "not_helpful": 0, "tags": []}]}]}