{"course_code": "IS435", "total_reviews": 1, "instructors": [{"professor_id": "1761785", "professor_name": "Maria Barraza", "avg_rating": 5.0, "avg_difficulty": 3.0, "review_count": 1, "reviews": [{"rating": 5.0, "difficulty": 3.0, "course_code": "IS435", "date": "Dec 4th, 2017", "metadata": {"For Credit": "Yes", "Attendance": "", "Would Take Again": "Yes", "Grade": "", "Textbook": "Yes"}, "review_msg": "Super informative and engaged, obviously interested in the subject matter. Very knowledgeable, but doesn't make you feel stupid. Hands down the best prof I've had!", "helpful": 0, "not_helpful": 0, "tags": ["Amazing lectures", "Would take again"]}]}]}