{"course_code": "JAP", "total_reviews": 2, "instructors": [{"professor_id": "14455", "professor_name": "Noriko Omae", "avg_rating": 1.75, "avg_difficulty": 4.5, "review_count": 2, "reviews": [{"rating": 1.0, "difficulty": 5.0, "course_code": "JAP", "date": "May 5th, 2004", "metadata": {"For Credit": "", "Attendance": "", "Would Take Again": "", "Grade": "", "Textbook": ""}, "review_msg": "people complain about her is bacause she plays favoritism.  YOu must be teacher's pet, that is why she liked you.", "helpful": 0, "not_helpful": 0, "tags": []}, {"rating": 2.5, "difficulty": 4.0, "course_code": "JAP", "date": "Apr 23rd, 2003", "metadata": {"For Credit": "", "Attendance": "", "Would Take Again": "", "Grade": "", "Textbook": ""}, "review_msg": "very picky.", "helpful": 0, "not_helpful": 0, "tags": []}]}]}