{"course_code": "LING104", "total_reviews": 1, "instructors": [{"professor_id": "136366", "professor_name": "Clifford Burgess", "avg_rating": 5.0, "avg_difficulty": 4.0, "review_count": 1, "reviews": [{"rating": 5.0, "difficulty": 4.0, "course_code": "LING104", "date": "Feb 24th, 2015", "metadata": {"For Credit": "Yes", "Attendance": "Mandatory", "Would Take Again": "", "Grade": "B+", "Textbook": "No"}, "review_msg": "He was simply fantastic. He was engaging with the class, deeply interested in the material and offered continual help. The subject matter wasn't for everyone but I have taken what he taught into real life context. It's a hard class and there is a lot of material but i thoroughly valued my experience with him.", "helpful": 1, "not_helpful": 2, "tags": []}]}]}