{"course_code": "1120SOCIOLOGY", "total_reviews": 1, "instructors": [{"professor_id": "1560730", "professor_name": "Elic Chan", "avg_rating": 4.5, "avg_difficulty": 3.0, "review_count": 1, "reviews": [{"rating": 4.5, "difficulty": 3.0, "course_code": "1120SOCIOLOGY", "date": "Dec 18th, 2014", "metadata": {"For Credit": "Yes", "Attendance": "Mandatory", "Would Take Again": "", "Grade": "A-", "Textbook": "Yes"}, "review_msg": "I took this class as an elective never previously having taken a Sociology class. The professor was clear and very engaging with the lectures, made it easy to understand. He is very helpful and will provide with all the necessary tools to get a good mark.", "helpful": 0, "not_helpful": 3, "tags": []}]}]}