{"course_code": "HUM151", "total_reviews": 1, "instructors": [{"professor_id": "36055", "professor_name": "Cs Morrissey", "avg_rating": 5.0, "avg_difficulty": 2.0, "review_count": 1, "reviews": [{"rating": 5.0, "difficulty": 2.0, "course_code": "HUM151", "date": "Sep 16th, 2002", "metadata": {"For Credit": "", "Attendance": "", "Would Take Again": "", "Grade": "", "Textbook": ""}, "review_msg": "He's the best prof ever! -easy going, patient, lots of fun! Must take his class!", "helpful": 0, "not_helpful": 0, "tags": []}]}]}