{"course_code": "GEOG1000", "total_reviews": 1, "instructors": [{"professor_id": "1359805", "professor_name": "Sharla Stolhandske", "avg_rating": 5.0, "avg_difficulty": 2.0, "review_count": 1, "reviews": [{"rating": 5.0, "difficulty": 2.0, "course_code": "GEOG1000", "date": "Mar 5th, 2019", "metadata": {"For Credit": "Yes", "Attendance": "Mandatory", "Would Take Again": "Yes", "Grade": "A-", "Textbook": "No"}, "review_msg": "SHE IS AMAZING", "helpful": 1, "not_helpful": 0, "tags": ["Respected", "Clear grading criteria", "Amazing lectures"]}]}]}