{"course_code": "EDUC371", "total_reviews": 1, "instructors": [{"professor_id": "2347043", "professor_name": "Jacqueline Barreiro", "avg_rating": 4.0, "avg_difficulty": 2.0, "review_count": 1, "reviews": [{"rating": 4.0, "difficulty": 2.0, "course_code": "EDUC371", "date": "Jun 14th, 2021", "metadata": {"For Credit": "Yes", "Attendance": "Mandatory", "Would Take Again": "Yes", "Grade": "A", "Textbook": "No"}, "review_msg": "She focused on curriculum and teaching theory. Her class was graded by several group projects, all of which are easy to succeed for students with an interest in education. Many international students also took the class as a grade booster which makes it even easier to score well for education students.", "helpful": 0, "not_helpful": 0, "tags": ["Participation matters", "Group projects"]}]}]}