{"course_code": "360", "total_reviews": 6, "instructors": [{"professor_id": "1256247", "professor_name": "Christian Venhuizen", "avg_rating": 2.0, "avg_difficulty": 5.0, "review_count": 1, "reviews": [{"rating": 2.0, "difficulty": 5.0, "course_code": "360", "date": "Nov 28th, 2014", "metadata": {"For Credit": "Yes", "Attendance": "", "Would Take Again": "", "Grade": "", "Textbook": "Yes"}, "review_msg": "He probably is a professor who always put people he like at the top and people he dont like at the bottom (No matter how good your submissions are). Don't take him if you are not good at making someone happy. Also, people from Asia should avoide him.", "helpful": 3, "not_helpful": 1, "tags": []}]}, {"professor_id": "40591", "professor_name": "Kevin Stewart", "avg_rating": 3.1, "avg_difficulty": 3.8, "review_count": 5, "reviews": [{"rating": 1.0, "difficulty": 5.0, "course_code": "360", "date": "Dec 17th, 2004", "metadata": {"For Credit": "", "Attendance": "", "Would Take Again": "", "Grade": "", "Textbook": ""}, "review_msg": "A terrible instructor! He is unclear about his expectation. He always says that your paper is not professional and he has his own convention. Totally unapproachable.", "helpful": 0, "not_helpful": 0, "tags": []}, {"rating": 3.0, "difficulty": 5.0, "course_code": "360", "date": "Dec 9th, 2004", "metadata": {"For Credit": "", "Attendance": "", "Would Take Again": "", "Grade": "", "Textbook": ""}, "review_msg": "why everybody not get back our report? he's so lazy and unfair", "helpful": 0, "not_helpful": 0, "tags": []}, {"rating": 3.5, "difficulty": 3.0, "course_code": "360", "date": "Dec 7th, 2003", "metadata": {"For Credit": "", "Attendance": "", "Would Take Again": "", "Grade": "", "Textbook": ""}, "review_msg": "a bit wordy", "helpful": 0, "not_helpful": 0, "tags": []}, {"rating": 5.0, "difficulty": 3.0, "course_code": "360", "date": "Nov 21st, 2002", "metadata": {"For Credit": "", "Attendance": "", "Would Take Again": "", "Grade": "", "Textbook": ""}, "review_msg": "Kevin is very helpful and approachable...", "helpful": 0, "not_helpful": 0, "tags": []}, {"rating": 3.0, "difficulty": 3.0, "course_code": "360", "date": "Nov 20th, 2002", "metadata": {"For Credit": "", "Attendance": "", "Would Take Again": "", "Grade": "", "Textbook": ""}, "review_msg": "No Comments", "helpful": 0, "not_helpful": 0, "tags": []}]}]}