{"course_code": "BUQU1230", "total_reviews": 2, "instructors": [{"professor_id": "2395730", "professor_name": "Maryam Dehghani Estakhri", "avg_rating": 4.0, "avg_difficulty": 2.0, "review_count": 2, "reviews": [{"rating": 3.0, "difficulty": 1.0, "course_code": "BUQU1230", "date": "Nov 25th, 2019", "metadata": {"For Credit": "Yes", "Attendance": "Mandatory", "Would Take Again": "No", "Grade": "B-", "Textbook": "No"}, "review_msg": "she is a nice person, who makes class fun, two assignments in her KPU class and two midterms. ONly one down fall is she does not mark your work on time. Our first assignment was marked last week of class. replies to emails slowly and takes for ev ver to mark. which was the most annoying part.", "helpful": 0, "not_helpful": 0, "tags": ["Accessible outside class", "Participation matters", "Amazing lectures"]}, {"rating": 5.0, "difficulty": 3.0, "course_code": "BUQU1230", "date": "Jul 31st, 2019", "metadata": {"For Credit": "", "Attendance": "Not Mandatory", "Would Take Again": "Yes", "Grade": "A+", "Textbook": "No"}, "review_msg": "Best prof , she is amazing teacher as well as very humble person. She is easily accessible after class and understands her students. Extremely fair on marking assignments and mid terms", "helpful": 0, "not_helpful": 0, "tags": ["Gives good feedback", "Respected", "Amazing lectures"]}]}]}