{"course_code": "ENSE460", "total_reviews": 1, "instructors": [{"professor_id": "968073", "professor_name": "Parvaneh Saeedi", "avg_rating": 4.0, "avg_difficulty": 4.0, "review_count": 1, "reviews": [{"rating": 4.0, "difficulty": 4.0, "course_code": "ENSE460", "date": "Nov 5th, 2007", "metadata": {"For Credit": "", "Attendance": "", "Would Take Again": "", "Grade": "", "Textbook": "Yes"}, "review_msg": "She is a good prof. She gives lots of work to do, makes you learn a lot. The slide notes were more words than pictures, lots of notes to read. She doesn't test them all though. The only thing is that she didn't award enough for the assignments, I mean they should worth more percentages in the course.", "helpful": 6, "not_helpful": 21, "tags": []}]}]}