{"professor_id": "2112515", "professor_name": "Ali Madooei", "overall_rating": "5", "would_take_again": "100", "difficulty_level": "2", "department": "Computer Science department", "total_ratings": "2", "reviews": [{"rating": "5.0", "difficulty": "2.0", "course_code": "CMPT102", "date": "Dec 23rd, 2016", "metadata": {"For Credit": "Yes", "Attendance": "Mandatory", "Would Take Again": "Yes", "Textbook": "Yes"}, "review_msg": "This was my first cmpt class and I was terrified. Madooei teaches topics really well and as long as you pay attention to class you wont have many problems with the assignments. If you understand the assignments  the midterm and final should be no problem. Overall hes a great prof and always wants to help you.", "helpful": "4", "not_helpful": "0", "tags": ["Hilarious", "Amazing lectures", "Caring"]}, {"rating": "5.0", "difficulty": "2.0", "course_code": "CMPT126", "date": "Mar 22nd, 2016", "metadata": {"For Credit": "Yes", "Textbook": "Yes"}, "review_msg": "Ali is an amazing lecturer and shows great respect for his students (he even brought cookies for us). He will definitely push you. In one semester, you can go from being a total C++ beginner to a master. However, the pace is definitely reasonable. Ali is very helpful and is always available at his office hours if you have any extra questions.", "helpful": "14", "not_helpful": "0", "tags": []}]}