{"professor_id": "222990", "professor_name": "Mike Volker", "overall_rating": "3.1", "would_take_again": "N/A", "difficulty_level": "3", "department": "Engineering department", "total_ratings": "10", "reviews": [{"rating": "5.0", "difficulty": "4.0", "course_code": "ENSC201", "date": "Dec 21st, 2009", "metadata": {"Textbook": "No"}, "review_msg": "It's too bad he doesn't teach 201 anymore. He is definitely in my top 3 teachers ever at SFU. Such an interesting person - his classes were great.", "helpful": "1", "not_helpful": "0", "tags": []}, {"rating": "5.0", "difficulty": "2.0", "course_code": "ENSC201", "date": "Jan 6th, 2008", "metadata": {"Textbook": "Yes"}, "review_msg": "Don't listen to these clowns. Mike Volker is a great teacher and a great mentor.", "helpful": "1", "not_helpful": "0", "tags": []}, {"rating": "1.0", "difficulty": "4.0", "course_code": "ENSC201", "date": "Jun 19th, 2006", "metadata": {}, "review_msg": "Full of crap. Doesn't cover most topics that assignments are based on. His notes contradict themselves and are inconsistent with assignment answers. Don't waste your time and money on his classes. F-", "helpful": "0", "not_helpful": "1", "tags": []}, {"rating": "2.5", "difficulty": "2.0", "course_code": "ENSC201", "date": "Sep 6th, 2005", "metadata": {"Attendance": "Mandatory", "Grade": "B"}, "review_msg": "Not so organized material, lots of it is the instructor's subjective point of view and interpretation of things. But a very informative and interesting course. Assignment q's are super vague- attend the lectures and try to guess what Mike thinks. Not a hard course to get an A+, so don't put too much effort in this course, but don't neglect it.", "helpful": "1", "not_helpful": "0", "tags": []}, {"rating": "3.0", "difficulty": "2.0", "course_code": "ENSC201", "date": "Mar 7th, 2005", "metadata": {"Attendance": "Mandatory"}, "review_msg": "great prof!", "helpful": "1", "not_helpful": "0", "tags": []}, {"rating": "3.5", "difficulty": "4.0", "course_code": "ENSC201", "date": "Nov 28th, 2003", "metadata": {}, "review_msg": "He is cool.", "helpful": "1", "not_helpful": "0", "tags": []}, {"rating": "1.0", "difficulty": "3.0", "course_code": "ENSC201", "date": "Jul 23rd, 2003", "metadata": {}, "review_msg": "This is one of the most useless profs ever.  Expect to learn random things that you will never need again.  Oh, and he's a jerk to boot!", "helpful": "0", "not_helpful": "1", "tags": []}, {"rating": "3.5", "difficulty": "3.0", "course_code": "ENSC201", "date": "Jun 30th, 2003", "metadata": {}, "review_msg": "He is good.", "helpful": "1", "not_helpful": "0", "tags": []}, {"rating": "3.0", "difficulty": "3.0", "course_code": "ENSC201", "date": "Jun 24th, 2003", "metadata": {}, "review_msg": "Not very helpful, the course material is unfocused and unorganized. Could be a lot better, but still not that terrible.", "helpful": "0", "not_helpful": "1", "tags": []}, {"rating": "3.5", "difficulty": "3.0", "course_code": "ENSC201", "date": "Jun 18th, 2003", "metadata": {}, "review_msg": "No Comments", "helpful": "0", "not_helpful": "0", "tags": []}]}