{"course_code": "160", "total_reviews": 1, "instructors": [{"professor_id": "1997100", "professor_name": "Debopam Das", "avg_rating": 1.0, "avg_difficulty": 4.0, "review_count": 1, "reviews": [{"rating": 1.0, "difficulty": 4.0, "course_code": "160", "date": "Oct 23rd, 2015", "metadata": {"For Credit": "Yes", "Attendance": "Not Mandatory", "Would Take Again": "", "Grade": "", "Textbook": "Yes"}, "review_msg": "Slides are summarized from the textbook (and he basically just reads off of them without adding anything extra). First midterm was super easy (finished in 20 min) and that seemed to offend him, so after that midterms because super obscure (questions based on single sentences in random parts of the chapters that aren't covered in class) DO NOT TAKE", "helpful": 7, "not_helpful": 0, "tags": []}]}]}